{
  "_note": "Manually curated 2026 Georgia election race data. Add one object per contested seat. Set activePhase to 'primary' or 'general' — flip it manually after primary results are confirmed. Populate general.candidates after the primary settles. See ga-elections-design.md for full schema documentation.",
  "_incumbentIds": "GA state member IDs (ocd-person/...) come from ga-members.json. Federal bioguideIds come from current-members.json. Find OCD IDs at openstates.org/ga/people/",
  "races": [
    {
      "id": "senate-2026",
      "level": "federal",
      "chamber": "U.S. Senate",
      "cycle": 2026,
      "activePhase": "primary",
      "phases": {
        "primary": {
          "electionDate": "2026-05-19",
          "primaryResult": "",
          "ballots": {
            "Democrat": [
              {
                "type": "incumbent",
                "memberId": "O000174",
                "memberSource": "congress"
              }
            ],
            "Republican": [
              {
                "type": "challenger",
                "id": "challenger-derek-dooley-senate-2026",
                "name": "Derek Dooley",
                "party": "Republican",
                "bio": "Consultant from Rabun County.",
                "imageUrl": "",
                "website": "https://dooleyforgeorgia.com"
              },
              {
                "type": "challenger",
                "id": "challenger-buddy-carter-senate-2026",
                "name": "Earl \"Buddy\" Carter",
                "party": "Republican",
                "bio": "Current U.S. Representative for Georgia's 1st Congressional District. Pharmacist.",
                "imageUrl": "",
                "website": "https://buddycarter.com"
              },
              {
                "type": "challenger",
                "id": "challenger-john-coyne-senate-2026",
                "name": "John Francis Coyne III",
                "party": "Republican",
                "bio": "CEO from Fulton County.",
                "imageUrl": "",
                "website": ""
              },
              {
                "type": "challenger",
                "id": "challenger-jonathan-mccolumn-senate-2026",
                "name": "Jonathan McColumn",
                "party": "Republican",
                "bio": "Brigadier General (Retired), U.S. Army.",
                "imageUrl": "",
                "website": "https://jonathanmccolumn.com"
              },
              {
                "type": "challenger",
                "id": "challenger-mike-collins-senate-2026",
                "name": "Michael Collins",
                "party": "Republican",
                "bio": "Current U.S. Representative for Georgia's 10th Congressional District.",
                "imageUrl": "",
                "website": "https://mikecollinsga.com"
              }
            ]
          }
        },
        "general": {
          "electionDate": "2026-11-03",
          "primaryResult": "",
          "candidates": []
        }
      }
    },
    {
      "id": "ga-06-2026",
      "level": "federal",
      "chamber": "U.S. House",
      "district": 6,
      "cycle": 2026,
      "activePhase": "primary",
      "phases": {
        "primary": {
          "electionDate": "2026-05-19",
          "primaryResult": "",
          "candidates": [
            {
              "type": "incumbent",
              "memberId": "A000374",
              "memberSource": "congress"
            }
          ]
        },
        "general": {
          "electionDate": "2026-11-03",
          "primaryResult": "",
          "candidates": []
        }
      }
    }
  ]
}

